{
  "meta": {
    "symbol": "NSE:TATACONSUM-EQ",
    "date": "2026-02-06",
    "resolution": "5",
    "fetched_at": "2026-02-13T14:30:01.412272Z"
  },
  "candles": [
    [
      1770349500,
      1146,
      1155.4,
      1146,
      1153.8,
      16503
    ],
    [
      1770349800,
      1153.7,
      1153.7,
      1152.2,
      1152.6,
      2692
    ],
    [
      1770350100,
      1152.8,
      1153.8,
      1152.1,
      1152.9,
      1579
    ],
    [
      1770350400,
      1152.8,
      1154.7,
      1150.5,
      1150.8,
      7561
    ],
    [
      1770350700,
      1150.8,
      1151.5,
      1148.5,
      1148.8,
      1246
    ],
    [
      1770351000,
      1148.8,
      1148.9,
      1147.3,
      1147.6,
      2757
    ],
    [
      1770351300,
      1147.6,
      1149.4,
      1147.6,
      1148.6,
      2360
    ],
    [
      1770351600,
      1148.6,
      1149.8,
      1147.3,
      1149.3,
      2418
    ],
    [
      1770351900,
      1148.6,
      1149.9,
      1148.2,
      1149.8,
      2195
    ],
    [
      1770352200,
      1149.9,
      1151.3,
      1149.9,
      1151.1,
      3941
    ],
    [
      1770352500,
      1150.6,
      1151.8,
      1149.6,
      1151.7,
      1756
    ],
    [
      1770352800,
      1151.5,
      1152,
      1150.3,
      1152,
      1488
    ],
    [
      1770353100,
      1152,
      1154.7,
      1151.1,
      1154.6,
      2361
    ],
    [
      1770353400,
      1154.6,
      1154.8,
      1152,
      1152.4,
      4113
    ],
    [
      1770353700,
      1152,
      1153.2,
      1150,
      1150,
      2133
    ],
    [
      1770354000,
      1150.6,
      1150.7,
      1149,
      1149.5,
      3167
    ],
    [
      1770354300,
      1149.5,
      1153,
      1149.3,
      1153,
      1408
    ],
    [
      1770354600,
      1152.6,
      1153.6,
      1151,
      1151.5,
      5780
    ],
    [
      1770354900,
      1151.4,
      1151.4,
      1147.6,
      1148.3,
      12063
    ],
    [
      1770355200,
      1148.3,
      1149.3,
      1147.5,
      1148.9,
      1612
    ],
    [
      1770355500,
      1148.9,
      1149.9,
      1148.5,
      1149.3,
      1817
    ],
    [
      1770355800,
      1149.3,
      1151.7,
      1149.1,
      1151.3,
      58054
    ],
    [
      1770356100,
      1151.4,
      1153,
      1151.4,
      1152.9,
      5447
    ],
    [
      1770356400,
      1152.9,
      1154.7,
      1152.5,
      1154.7,
      2238
    ],
    [
      1770356700,
      1155,
      1155,
      1151.7,
      1152.8,
      10286
    ],
    [
      1770357000,
      1152.8,
      1155,
      1152.7,
      1154,
      9102
    ],
    [
      1770357300,
      1154,
      1154,
      1150.6,
      1151.3,
      19671
    ],
    [
      1770357600,
      1151.2,
      1153.1,
      1150.3,
      1151.2,
      19842
    ],
    [
      1770357900,
      1151.6,
      1155.9,
      1151,
      1154.1,
      24885
    ],
    [
      1770358200,
      1154.8,
      1155.9,
      1153,
      1153.4,
      5004
    ],
    [
      1770358500,
      1153.4,
      1153.8,
      1151.8,
      1152.9,
      4811
    ],
    [
      1770358800,
      1153.2,
      1154.5,
      1150.5,
      1151,
      30627
    ],
    [
      1770359100,
      1151,
      1151.9,
      1150.7,
      1151.8,
      2666
    ],
    [
      1770359400,
      1151.8,
      1152,
      1151,
      1151.3,
      10046
    ],
    [
      1770359700,
      1151,
      1151.3,
      1149.3,
      1149.8,
      4541
    ],
    [
      1770360000,
      1149.8,
      1150.6,
      1148.6,
      1150,
      12680
    ],
    [
      1770360300,
      1150,
      1150,
      1148.8,
      1149.3,
      4182
    ],
    [
      1770360600,
      1149.3,
      1150.6,
      1149.2,
      1150,
      22939
    ],
    [
      1770360900,
      1150,
      1152.3,
      1149.2,
      1152.3,
      15018
    ],
    [
      1770361200,
      1152.3,
      1152.4,
      1149.5,
      1150.4,
      10498
    ],
    [
      1770361500,
      1150.4,
      1151.9,
      1150.4,
      1151.5,
      2161
    ],
    [
      1770361800,
      1151.5,
      1151.8,
      1150.4,
      1151,
      3419
    ],
    [
      1770362100,
      1151,
      1152.9,
      1149.5,
      1149.6,
      4348
    ],
    [
      1770362400,
      1149.6,
      1150,
      1149.1,
      1150,
      1929
    ],
    [
      1770362700,
      1149.7,
      1150.5,
      1149.4,
      1149.9,
      29410
    ],
    [
      1770363000,
      1150,
      1150,
      1148.9,
      1149.6,
      2787
    ],
    [
      1770363300,
      1149.6,
      1150,
      1149.6,
      1149.9,
      3371
    ],
    [
      1770363600,
      1150,
      1151,
      1149.9,
      1150.7,
      40951
    ],
    [
      1770363900,
      1150.9,
      1152.3,
      1150.2,
      1151.8,
      9396
    ],
    [
      1770364200,
      1152.2,
      1153.1,
      1151.6,
      1152.2,
      6171
    ],
    [
      1770364500,
      1152.2,
      1152.3,
      1150.5,
      1151.8,
      7929
    ],
    [
      1770364800,
      1151.8,
      1152.3,
      1150.8,
      1152,
      24931
    ],
    [
      1770365100,
      1152,
      1153.5,
      1151.6,
      1153.5,
      10322
    ],
    [
      1770365400,
      1153.5,
      1154.8,
      1153.5,
      1154.7,
      2402
    ],
    [
      1770365700,
      1154.7,
      1155.9,
      1153.6,
      1155.4,
      7988
    ],
    [
      1770366000,
      1155.4,
      1157.1,
      1155,
      1156.7,
      5306
    ],
    [
      1770366300,
      1156.7,
      1158.4,
      1156.4,
      1157.9,
      5877
    ],
    [
      1770366600,
      1157.9,
      1159,
      1157.5,
      1158.5,
      3590
    ],
    [
      1770366900,
      1158.5,
      1158.8,
      1156.1,
      1157.5,
      7194
    ],
    [
      1770367200,
      1157.5,
      1158,
      1156.6,
      1157.8,
      2492
    ],
    [
      1770367500,
      1158,
      1158,
      1156.2,
      1157.4,
      3329
    ],
    [
      1770367800,
      1157.4,
      1158,
      1156.3,
      1156.4,
      3899
    ],
    [
      1770368100,
      1156.9,
      1157.9,
      1156.4,
      1157.9,
      2129
    ],
    [
      1770368400,
      1157.9,
      1157.9,
      1154.4,
      1154.4,
      17575
    ],
    [
      1770368700,
      1154.4,
      1155.1,
      1154.1,
      1155,
      12620
    ],
    [
      1770369000,
      1155,
      1155,
      1154.1,
      1154.9,
      12995
    ],
    [
      1770369300,
      1155,
      1155,
      1152.2,
      1153,
      10380
    ],
    [
      1770369600,
      1153,
      1153.4,
      1151.2,
      1152,
      37504
    ],
    [
      1770369900,
      1152,
      1155.6,
      1151.8,
      1155.6,
      21947
    ],
    [
      1770370200,
      1156.8,
      1158.6,
      1156.5,
      1158.2,
      29062
    ],
    [
      1770370500,
      1158.1,
      1159.3,
      1158,
      1158.7,
      24591
    ],
    [
      1770370800,
      1158.4,
      1160,
      1157.5,
      1159.9,
      24929
    ],
    [
      1770371100,
      1159.8,
      1160.3,
      1159.5,
      1159.8,
      28277
    ],
    [
      1770371400,
      1159.6,
      1161.2,
      1159,
      1161.2,
      33973
    ],
    [
      1770371700,
      1161.2,
      1161.8,
      1158.6,
      1161.3,
      27692
    ]
  ]
}