{
  "meta": {
    "symbol": "NSE:HEROMOTOCO-EQ",
    "date": "2026-02-09",
    "resolution": "5",
    "fetched_at": "2026-02-13T14:30:10.370675Z"
  },
  "candles": [
    [
      1770608700,
      5800,
      5816,
      5667,
      5686.5,
      42911
    ],
    [
      1770609000,
      5686.5,
      5694.5,
      5674,
      5693.5,
      13651
    ],
    [
      1770609300,
      5693.5,
      5737,
      5690,
      5720,
      15881
    ],
    [
      1770609600,
      5721,
      5740,
      5700,
      5700,
      10972
    ],
    [
      1770609900,
      5701,
      5706.5,
      5694,
      5699.5,
      6443
    ],
    [
      1770610200,
      5699,
      5700,
      5687,
      5698,
      7062
    ],
    [
      1770610500,
      5698,
      5722,
      5693,
      5722,
      9129
    ],
    [
      1770610800,
      5724.5,
      5749.5,
      5724.5,
      5736.5,
      9775
    ],
    [
      1770611100,
      5735,
      5743,
      5734,
      5742,
      7761
    ],
    [
      1770611400,
      5742,
      5752,
      5740,
      5747.5,
      9640
    ],
    [
      1770611700,
      5747.5,
      5754,
      5737,
      5742,
      6335
    ],
    [
      1770612000,
      5745,
      5746,
      5722.5,
      5725.5,
      5270
    ],
    [
      1770612300,
      5725.5,
      5733.5,
      5725.5,
      5732,
      2303
    ],
    [
      1770612600,
      5734.5,
      5738,
      5731,
      5733,
      2722
    ],
    [
      1770612900,
      5733,
      5740.5,
      5728,
      5731.5,
      3115
    ],
    [
      1770613200,
      5731.5,
      5735.5,
      5731,
      5734,
      2591
    ],
    [
      1770613500,
      5735,
      5741.5,
      5734,
      5740.5,
      3008
    ],
    [
      1770613800,
      5740.5,
      5744,
      5733,
      5741,
      4595
    ],
    [
      1770614100,
      5741,
      5743.5,
      5733,
      5734,
      3585
    ],
    [
      1770614400,
      5734,
      5740,
      5730,
      5736.5,
      5316
    ],
    [
      1770614700,
      5736.5,
      5738,
      5727.5,
      5729,
      3672
    ],
    [
      1770615000,
      5729,
      5732,
      5721,
      5723.5,
      7297
    ],
    [
      1770615300,
      5723.5,
      5729.5,
      5723.5,
      5726.5,
      2784
    ],
    [
      1770615600,
      5725,
      5726.5,
      5712.5,
      5716.5,
      4805
    ],
    [
      1770615900,
      5716.5,
      5723,
      5714.5,
      5722,
      1823
    ],
    [
      1770616200,
      5722,
      5730,
      5722,
      5730,
      2940
    ],
    [
      1770616500,
      5729.5,
      5730,
      5722.5,
      5723.5,
      2871
    ],
    [
      1770616800,
      5723.5,
      5724,
      5720,
      5723,
      1491
    ],
    [
      1770617100,
      5723,
      5742,
      5723,
      5730,
      5608
    ],
    [
      1770617400,
      5729.5,
      5762,
      5727,
      5752.5,
      10524
    ],
    [
      1770617700,
      5754.5,
      5758.5,
      5743.5,
      5746.5,
      4737
    ],
    [
      1770618000,
      5746.5,
      5746.5,
      5734,
      5737.5,
      3105
    ],
    [
      1770618300,
      5737.5,
      5742.5,
      5734.5,
      5740,
      3804
    ],
    [
      1770618600,
      5740,
      5744,
      5739.5,
      5744,
      1353
    ],
    [
      1770618900,
      5744.5,
      5747,
      5742.5,
      5747,
      2142
    ],
    [
      1770619200,
      5747,
      5749.5,
      5746.5,
      5748,
      2264
    ],
    [
      1770619500,
      5748,
      5750,
      5747.5,
      5747.5,
      1479
    ],
    [
      1770619800,
      5747.5,
      5749,
      5747,
      5749,
      1041
    ],
    [
      1770620100,
      5749,
      5749,
      5740,
      5740,
      1666
    ],
    [
      1770620400,
      5740,
      5740,
      5731.5,
      5734.5,
      2799
    ],
    [
      1770620700,
      5734.5,
      5741,
      5734.5,
      5741,
      2107
    ],
    [
      1770621000,
      5741,
      5744,
      5735.5,
      5736,
      2309
    ],
    [
      1770621300,
      5735.5,
      5737.5,
      5731.5,
      5732.5,
      2492
    ],
    [
      1770621600,
      5733,
      5736,
      5730,
      5733,
      3248
    ],
    [
      1770621900,
      5733,
      5735,
      5730,
      5735,
      2823
    ],
    [
      1770622200,
      5735,
      5735,
      5724.5,
      5729,
      7159
    ],
    [
      1770622500,
      5730,
      5735,
      5729,
      5734,
      3611
    ],
    [
      1770622800,
      5735,
      5735,
      5729.5,
      5731,
      1479
    ],
    [
      1770623100,
      5731,
      5735,
      5729,
      5733.5,
      2334
    ],
    [
      1770623400,
      5735,
      5735,
      5730,
      5731.5,
      2146
    ],
    [
      1770623700,
      5732,
      5735,
      5731,
      5733.5,
      4764
    ],
    [
      1770624000,
      5733.5,
      5744.5,
      5733.5,
      5743.5,
      5872
    ],
    [
      1770624300,
      5745,
      5758,
      5744,
      5751,
      5769
    ],
    [
      1770624600,
      5751,
      5755,
      5749,
      5753,
      4896
    ],
    [
      1770624900,
      5753,
      5753,
      5743.5,
      5745,
      4309
    ],
    [
      1770625200,
      5744.5,
      5748.5,
      5742,
      5744,
      4705
    ],
    [
      1770625500,
      5744,
      5747,
      5742.5,
      5743.5,
      5408
    ],
    [
      1770625800,
      5743.5,
      5746,
      5736,
      5740.5,
      6177
    ],
    [
      1770626100,
      5740.5,
      5740.5,
      5737.5,
      5738,
      1869
    ],
    [
      1770626400,
      5738.5,
      5738.5,
      5734,
      5735,
      5058
    ],
    [
      1770626700,
      5735,
      5745.5,
      5735,
      5740,
      5695
    ],
    [
      1770627000,
      5740,
      5750,
      5738.5,
      5743.5,
      6441
    ],
    [
      1770627300,
      5743,
      5745,
      5740.5,
      5744,
      1689
    ],
    [
      1770627600,
      5744,
      5745,
      5741.5,
      5743.5,
      2652
    ],
    [
      1770627900,
      5743.5,
      5745,
      5743,
      5745,
      1313
    ],
    [
      1770628200,
      5745,
      5745,
      5738.5,
      5739.5,
      2101
    ],
    [
      1770628500,
      5739,
      5750,
      5739,
      5747.5,
      12233
    ],
    [
      1770628800,
      5747.5,
      5747.5,
      5738,
      5741,
      11736
    ],
    [
      1770629100,
      5742,
      5763,
      5742,
      5757.5,
      31311
    ],
    [
      1770629400,
      5757.5,
      5768.5,
      5754,
      5759,
      20992
    ],
    [
      1770629700,
      5759,
      5762,
      5754.5,
      5755,
      16380
    ],
    [
      1770630000,
      5755,
      5755.5,
      5745.5,
      5751.5,
      25185
    ],
    [
      1770630300,
      5751,
      5768,
      5751,
      5758,
      26477
    ],
    [
      1770630600,
      5758.5,
      5768,
      5751.5,
      5755,
      30865
    ],
    [
      1770630900,
      5754,
      5754.5,
      5748,
      5748,
      26734
    ]
  ]
}